brain_games/__init__.py
brain_games/cli.py
brain_games/engine.py
brain_games/games/__init__.py
brain_games/games/calc.py
brain_games/games/even.py
brain_games/games/gcd.py
brain_games/games/prime.py
brain_games/games/progression.py
brain_games/scripts/brain_calc.py
brain_games/scripts/brain_even.py
brain_games/scripts/brain_games.py
brain_games/scripts/brain_gcd.py
brain_games/scripts/brain_prime.py
brain_games/scripts/brain_progression.py
postscriptumno_brain_games-0.1.16.dist-info/entry_points.txt
postscriptumno_brain_games-0.1.16.dist-info/WHEEL
postscriptumno_brain_games-0.1.16.dist-info/METADATA
postscriptumno_brain_games-0.1.16.dist-info/RECORD
