Metadata-Version: 2.1
Name: postscriptumno-brain-games
Version: 0.1.16
Summary: Brain games project
Home-page: https://github.com/postscriptumno/python-project-lvl1
Author: postscriptumno
Author-email: postscriptum.no@gmail.com
Requires-Python: >=3.8,<4.0
Classifier: Programming Language :: Python :: 3
Classifier: Programming Language :: Python :: 3.8
Requires-Dist: prompt (>=0.4.1,<0.5.0)
Project-URL: Repository, https://github.com/postscriptumno/python-project-lvl1
